zuinnote/__init__.py
zuinnote/scrapy/__init__.py
zuinnote/scrapy/contrib/__init__.py
zuinnote/scrapy/contrib/bigexporters.py
scrapy_contrib_bigexporters-0.6.1.dist-info/licenses/LICENSE
scrapy_contrib_bigexporters-0.6.1.dist-info/WHEEL
scrapy_contrib_bigexporters-0.6.1.dist-info/METADATA
scrapy_contrib_bigexporters-0.6.1.dist-info/RECORD
