Metadata-Version: 2.4
Name: scrapy-contrib-bigexporters
Version: 0.6.1
Summary: Scrapy exporter for Big Data formats
Author-email: Jörn Franke <oss@zuinnote.eu>
Requires-Python: >=3.12
Classifier: Development Status :: 5 - Production/Stable
Classifier: Intended Audience :: Developers
Classifier: License :: OSI Approved :: MIT License
Classifier: Programming Language :: Python
Classifier: Programming Language :: Python :: 3
Classifier: Programming Language :: Python :: 3.11
Classifier: Programming Language :: Python :: 3.12
Classifier: Programming Language :: Python :: 3.13
Classifier: Programming Language :: Python :: 3.14
Classifier: Topic :: Software Development :: Libraries
Classifier: Operating System :: OS Independent
License-File: LICENSE
Requires-Dist: Scrapy>=2.13.3
Requires-Dist: fastavro>=1.12.0 ; extra == "avro"
Requires-Dist: black>=25.9.0 ; extra == "dev"
Requires-Dist: prospector>=1.17.0 ; extra == "dev"
Requires-Dist: pylint>=3.3.0 ; extra == "dev"
Requires-Dist: bandit>=1.8.0 ; extra == "dev"
Requires-Dist: pycodestyle>=2.14.0 ; extra == "dev"
Requires-Dist: mccabe>=0.7.0 ; extra == "dev"
Requires-Dist: mypy>=1.18.0 ; extra == "dev"
Requires-Dist: sphinx>=8.2.0 ; extra == "doc"
Requires-Dist: pyiceberg>=0.10.0 ; extra == "iceberg"
Requires-Dist: pyarrow ; extra == "iceberg"
Requires-Dist: pyorc>=0.10.0 ; extra == "orc"
Requires-Dist: fastparquet>=2024.11.0 ; extra == "parquet"
Requires-Dist: pandas>=2.2.0 ; extra == "parquet"
Requires-Dist: pyiceberg[sql-sqlite]>=0.10 ; extra == "test"
Requires-Dist: coverage>=7.10 ; extra == "test"
Requires-Dist: tox>=4.30.0 ; extra == "test"
Requires-Dist: pytest>=8.4.0 ; extra == "test"
Project-URL: documentation, https://codeberg.org/ZuInnoTe/scrapy-contrib-bigexporters
Project-URL: download, https://codeberg.org/ZuInnoTe/scrapy-contrib-bigexporters
Project-URL: homepage, https://codeberg.org/ZuInnoTe/scrapy-contrib-bigexporters
Project-URL: source, https://codeberg.org/ZuInnoTe/scrapy-contrib-bigexporters
Project-URL: tracker, https://codeberg.org/ZuInnoTe/scrapy-contrib-bigexporters/issues
Provides-Extra: avro
Provides-Extra: dev
Provides-Extra: doc
Provides-Extra: iceberg
Provides-Extra: orc
Provides-Extra: parquet
Provides-Extra: test
